{
  "class": {
    "name": "Word.CustomXmlNode",
    "package": "word",
    "extends": [
      "OfficeExtension.ClientObject"
    ],
    "api_set": {
      "name": "WordApi",
      "status": "BETA (PREVIEW ONLY)"
    },
    "description": "Represents an XML node in a tree in the document. The CustomXmlNode object is a member of the Word.CustomXmlNodeCollection object: https://learn.microsoft.com/en-us/javascript/api/word/word.customxmlnodecollection",
    "examples": []
  },
  "properties": [
    {
      "name": "attributes",
      "type": "Word.CustomXmlNodeCollection",
      "description": "Gets a CustomXmlNodeCollection object representing the attributes of the current element in the current node.",
      "since": "WordApi BETA (PREVIEW ONLY)",
      "examples": []
    },
    {
      "name": "baseName",
      "type": "string",
      "description": "Gets the base name of the node without the namespace prefix, if one exists.",
      "since": "WordApi BETA (PREVIEW ONLY)",
      "examples": []
    },
    {
      "name": "childNodes",
      "type": "Word.CustomXmlNodeCollection",
      "description": "Gets a CustomXmlNodeCollection object containing all of the child elements of the current node.",
      "since": "WordApi BETA (PREVIEW ONLY)",
      "examples": []
    },
    {
      "name": "context",
      "type": "RequestContext",
      "description": "The request context associated with the object. This connects the add-in's process to the Office host application's process.",
      "since": null,
      "examples": []
    },
    {
      "name": "firstChild",
      "type": "Word.CustomXmlNode",
      "description": "Gets a CustomXmlNode object corresponding to the first child element of the current node. If the node has no child elements (or if it isn't of type CustomXmlNodeType.element), returns `Nothing`.",
      "since": "WordApi BETA (PREVIEW ONLY)",
      "examples": []
    },
    {
      "name": "lastChild",
      "type": "Word.CustomXmlNode",
      "description": "Gets a CustomXmlNode object corresponding to the last child element of the current node. If the node has no child elements (or if it isn't of type CustomXmlNodeType.element), the property returns `Nothing`.",
      "since": "WordApi BETA (PREVIEW ONLY)",
      "examples": []
    },
    {
      "name": "namespaceUri",
      "type": "string",
      "description": "Gets the unique address identifier for the namespace of the node.",
      "since": "WordApi BETA (PREVIEW ONLY)",
      "examples": []
    },
    {
      "name": "nextSibling",
      "type": "Word.CustomXmlNode",
      "description": "Gets the next sibling node (element, comment, or processing instruction) of the current node. If the node is the last sibling at its level, the property returns `Nothing`.",
      "since": "WordApi BETA (PREVIEW ONLY)",
      "examples": []
    },
    {
      "name": "nodeType",
      "type": "Word.CustomXmlNodeType | \"element\" | \"attribute\" | \"text\" | \"cData\" | \"processingInstruction\" | \"comment\" | \"document\"",
      "description": "Gets the type of the current node.",
      "since": "WordApi BETA (PREVIEW ONLY)",
      "examples": []
    },
    {
      "name": "nodeValue",
      "type": "string",
      "description": "Specifies the value of the current node.",
      "since": "WordApi BETA (PREVIEW ONLY)",
      "examples": []
    },
    {
      "name": "ownerPart",
      "type": "Word.CustomXmlPart",
      "description": "Gets the object representing the part associated with this node.",
      "since": "WordApi BETA (PREVIEW ONLY)",
      "examples": []
    },
    {
      "name": "parentNode",
      "type": "Word.CustomXmlNode",
      "description": "Gets the parent element node of the current node. If the current node is at the root level, the property returns `Nothing`.",
      "since": "WordApi BETA (PREVIEW ONLY)",
      "examples": []
    },
    {
      "name": "previousSibling",
      "type": "Word.CustomXmlNode",
      "description": "Gets the previous sibling node (element, comment, or processing instruction) of the current node. If the current node is the first sibling at its level, the property returns `Nothing`.",
      "since": "WordApi BETA (PREVIEW ONLY)",
      "examples": []
    },
    {
      "name": "text",
      "type": "string",
      "description": "Specifies the text for the current node.",
      "since": "WordApi BETA (PREVIEW ONLY)",
      "examples": []
    },
    {
      "name": "xml",
      "type": "string",
      "description": "Gets the XML representation of the current node and its children.",
      "since": "WordApi BETA (PREVIEW ONLY)",
      "examples": []
    },
    {
      "name": "xpath",
      "type": "string",
      "description": "Gets a string with the canonicalized XPath for the current node. If the node is no longer in the Document Object Model (DOM), the property returns an error message.",
      "since": "WordApi BETA (PREVIEW ONLY)",
      "examples": []
    }
  ],
  "methods": [
    {
      "name": "appendChildNode",
      "kind": "create",
      "description": "Appends a single node as the last child under the context element node in the tree.",
      "signatures": [
        {
          "params": [
            {
              "name": "options",
              "type": "Word.CustomXmlAppendChildNodeOptions",
              "required": false,
              "description": "Optional. The options that define the node to be appended."
            }
          ],
          "returns": {
            "type": "OfficeExtension.ClientResult<number>",
            "description": null
          }
        }
      ],
      "examples": []
    },
    {
      "name": "appendChildSubtree",
      "kind": "create",
      "description": "Adds a subtree as the last child under the context element node in the tree.",
      "signatures": [
        {
          "params": [
            {
              "name": "xml",
              "type": "string",
              "required": true,
              "description": "A string representing the XML subtree."
            }
          ],
          "returns": {
            "type": "OfficeExtension.ClientResult<number>",
            "description": null
          }
        }
      ],
      "examples": []
    },
    {
      "name": "delete",
      "kind": "delete",
      "description": "Deletes the current node from the tree (including all of its children, if any exist).",
      "signatures": [
        {
          "params": [],
          "returns": {
            "type": "void",
            "description": null
          }
        }
      ],
      "examples": []
    },
    {
      "name": "hasChildNodes",
      "kind": "read",
      "description": "Specifies if the current element node has child element nodes.",
      "signatures": [
        {
          "params": [],
          "returns": {
            "type": "OfficeExtension.ClientResult<boolean>",
            "description": null
          }
        }
      ],
      "examples": []
    },
    {
      "name": "insertNodeBefore",
      "kind": "create",
      "description": "Inserts a new node just before the context node in the tree.",
      "signatures": [
        {
          "params": [
            {
              "name": "options",
              "type": "Word.CustomXmlInsertNodeBeforeOptions",
              "required": false,
              "description": "Optional. The options that define the node to be inserted."
            }
          ],
          "returns": {
            "type": "OfficeExtension.ClientResult<number>",
            "description": null
          }
        }
      ],
      "examples": []
    },
    {
      "name": "insertSubtreeBefore",
      "kind": "create",
      "description": "Inserts the specified subtree into the location just before the context node.",
      "signatures": [
        {
          "params": [
            {
              "name": "xml",
              "type": "string",
              "required": true,
              "description": "A string representing the XML subtree."
            },
            {
              "name": "options",
              "type": "Word.CustomXmlInsertSubtreeBeforeOptions",
              "required": false,
              "description": "Optional. The options available for inserting the subtree."
            }
          ],
          "returns": {
            "type": "OfficeExtension.ClientResult<number>",
            "description": null
          }
        }
      ],
      "examples": []
    },
    {
      "name": "load",
      "kind": "load",
      "description": "Queues up a command to load the specified properties of the object. You must call `context.sync()` before reading the properties.",
      "signatures": [
        {
          "params": [
            {
              "name": "options",
              "type": "Word.Interfaces.CustomXmlNodeLoadOptions",
              "required": false,
              "description": "Provides options for which properties of the object to load."
            }
          ],
          "returns": {
            "type": "Word.CustomXmlNode",
            "description": null
          }
        },
        {
          "params": [
            {
              "name": "propertyNames",
              "type": "string | string[]",
              "required": false,
              "description": "A comma-delimited string or an array of strings that specify the properties to load."
            }
          ],
          "returns": {
            "type": "Word.CustomXmlNode",
            "description": null
          }
        },
        {
          "params": [
            {
              "name": "propertyNamesAndPaths",
              "type": "{ select?: string; expand?: string; }",
              "required": false,
              "description": "`propertyNamesAndPaths.select` is a comma-delimited string that specifies the properties to load, and `propertyNamesAndPaths.expand` is a comma-delimited string that specifies the navigation properties to load."
            }
          ],
          "returns": {
            "type": "Word.CustomXmlNode",
            "description": null
          }
        }
      ],
      "examples": []
    },
    {
      "name": "removeChild",
      "kind": "delete",
      "description": "Removes the specified child node from the tree.",
      "signatures": [
        {
          "params": [
            {
              "name": "child",
              "type": "Word.CustomXmlNode",
              "required": true,
              "description": "The child node to remove."
            }
          ],
          "returns": {
            "type": "OfficeExtension.ClientResult<number>",
            "description": null
          }
        }
      ],
      "examples": []
    },
    {
      "name": "replaceChildNode",
      "kind": "write",
      "description": "Removes the specified child node and replaces it with a different node in the same location.",
      "signatures": [
        {
          "params": [
            {
              "name": "oldNode",
              "type": "Word.CustomXmlNode",
              "required": true,
              "description": "The node to be replaced."
            },
            {
              "name": "options",
              "type": "Word.CustomXmlReplaceChildNodeOptions",
              "required": false,
              "description": "Optional. The options that define the child node which is to replace the old node."
            }
          ],
          "returns": {
            "type": "OfficeExtension.ClientResult<number>",
            "description": null
          }
        }
      ],
      "examples": []
    },
    {
      "name": "replaceChildSubtree",
      "kind": "write",
      "description": "Removes the specified node and replaces it with a different subtree in the same location.",
      "signatures": [
        {
          "params": [
            {
              "name": "xml",
              "type": "string",
              "required": true,
              "description": "A string representing the new subtree."
            },
            {
              "name": "oldNode",
              "type": "Word.CustomXmlNode",
              "required": true,
              "description": "The node to be replaced."
            }
          ],
          "returns": {
            "type": "OfficeExtension.ClientResult<number>",
            "description": null
          }
        }
      ],
      "examples": []
    },
    {
      "name": "selectNodes",
      "kind": "read",
      "description": "Selects a collection of nodes matching an XPath expression.",
      "signatures": [
        {
          "params": [
            {
              "name": "xPath",
              "type": "string",
              "required": true,
              "description": "The XPath expression."
            }
          ],
          "returns": {
            "type": "Word.CustomXmlNodeCollection",
            "description": null
          }
        }
      ],
      "examples": []
    },
    {
      "name": "selectSingleNode",
      "kind": "read",
      "description": "Selects a single node from a collection matching an XPath expression.",
      "signatures": [
        {
          "params": [
            {
              "name": "xPath",
              "type": "string",
              "required": true,
              "description": "The XPath expression."
            }
          ],
          "returns": {
            "type": "Word.CustomXmlNode",
            "description": null
          }
        }
      ],
      "examples": []
    },
    {
      "name": "set",
      "kind": "write",
      "description": "Sets multiple properties of an object at the same time. You can pass either a plain object with the appropriate properties, or another API object of the same type.",
      "signatures": [
        {
          "params": [
            {
              "name": "properties",
              "type": "Interfaces.CustomXmlNodeUpdateData",
              "required": true,
              "description": "A JavaScript object with properties that are structured isomorphically to the properties of the object on which the method is called."
            },
            {
              "name": "options",
              "type": "OfficeExtension.UpdateOptions",
              "required": false,
              "description": "Provides an option to suppress errors if the properties object tries to set any read-only properties."
            }
          ],
          "returns": {
            "type": "void",
            "description": null
          }
        },
        {
          "params": [
            {
              "name": "properties",
              "type": "Word.CustomXmlNode",
              "required": true,
              "description": null
            }
          ],
          "returns": {
            "type": "void",
            "description": null
          }
        }
      ],
      "examples": []
    },
    {
      "name": "toJSON",
      "kind": "serialize",
      "description": "Overrides the JavaScript `toJSON()` method in order to provide more useful output when an API object is passed to `JSON.stringify()`. (`JSON.stringify`, in turn, calls the `toJSON` method of the object that's passed to it.) Whereas the original `Word.CustomXmlNode` object is an API object, the `toJSON` method returns a plain JavaScript object (typed as `Word.Interfaces.CustomXmlNodeData`) that contains shallow copies of any loaded child properties from the original object.",
      "signatures": [
        {
          "params": [],
          "returns": {
            "type": "Word.Interfaces.CustomXmlNodeData",
            "description": null
          }
        }
      ],
      "examples": []
    },
    {
      "name": "track",
      "kind": "track",
      "description": "Track the object for automatic adjustment based on surrounding changes in the document. This call is a shorthand for context.trackedObjects.add(thisObject). If you're using this object across `.sync` calls and outside the sequential execution of a \".run\" batch, and get an \"InvalidObjectPath\" error when setting a property or invoking a method on the object, you need to add the object to the tracked object collection when the object was first created. If this object is part of a collection, you should also track the parent collection.",
      "signatures": [
        {
          "params": [],
          "returns": {
            "type": "Word.CustomXmlNode",
            "description": null
          }
        }
      ],
      "examples": []
    },
    {
      "name": "untrack",
      "kind": "untrack",
      "description": "Release the memory associated with this object, if it has previously been tracked. This call is shorthand for context.trackedObjects.remove(thisObject). Having many tracked objects slows down the host application, so please remember to free any objects you add, once you're done using them. You'll need to call `context.sync()` before the memory release takes effect.",
      "signatures": [
        {
          "params": [],
          "returns": {
            "type": "Word.CustomXmlNode",
            "description": null
          }
        }
      ],
      "examples": []
    }
  ],
  "source": {
    "urls": [
      "https://learn.microsoft.com/en-us/javascript/api/word/word.customxmlnode"
    ]
  }
}